[
    {
        "_id": "5ee06aa44fb3ab0569961359",
        "text": "Cooooool.....",
        "user": "5ee04a3f36836502ba8415f8",
        "post": "5ee05ed99790510437b5402e"
    },
    {
        "_id": "5ee06b43f1e9fe05b910ac59",
        "text": "Awesome",
        "user": "5ee04a3f36836502ba8415f8",
        "post": "5ee05ddb665eb803beba5415"
    },
    {
        "_id": "5ee06c97f1e9fe05b910ac5e",
        "text": "Looks Fun",
        "user": "5ee04a3f36836502ba8415fc",
        "post": "5ee05ddb665eb803beba5415"
    },
    {
        "_id": "5ee06c01f1e9fe05b910ac5c",
        "text": "WOW... JUST WOW",
        "user": "5ee04a3f36836502ba8415f9",
        "post": "5ee05a45c5106d01f80d8e6d"
    },
    {
        "_id": "5ee06c56f1e9fe05b910ac5d",
        "text": "SUEPER COOOOOOOOOOOL !!",
        "user": "5ee04a3f36836502ba8415fc",
        "post": "5ee05aad4fd11f0229d0e0cf"
    },
    {
        "_id": "5ee06bc7f1e9fe05b910ac5b",
        "text": "sad life..",
        "user": "5ee04a3f36836502ba8415f9",
        "post": "5ee05e9ef0c36e041099b15d"
    },
    {
        "_id": "5ee06b76f1e9fe05b910ac5a",
        "text": "HAPPY HOLI :) ",
        "user": "5ee04a3f36836502ba8415f8",
        "post": "5ee05dac665eb803beba5414"
    },
    {
        "_id": "5ee06af727605405a0e77679",
        "text": "Looks yummy...",
        "user": "5ee04a3f36836502ba8415f8",
        "post": "5ee05e343f306803f5457656"
    }
]